{"stats":{"minecraft:dropped":{"vanilla_plus:black_stained_glass_stairs":1,"vanilla_plus:black_terracotta_stairs":1,"vanilla_plus:sand_stairs":1,"minecraft:dirt":1,"vanilla_plus:dirt_stairs":2,"minecraft:sand":1,"vanilla_plus:glass_stairs":1,"vanilla_plus:block_of_amethyst_stairs":1,"vanilla_plus:black_concrete_stairs":2,"vanilla_plus:dirt_slab":1,"vanilla_plus:grass_block_stairs":1,"vanilla_plus:black_concrete_powder_stairs":1,"vanilla_plus:glowstone_stairs":1,"vanilla_plus:black_wool_stairs":1,"vanilla_plus:oak_log":1},"minecraft:used":{"vanilla_plus:black_wool_stairs":2,"vanilla_plus:glass_stairs":8,"vanilla_plus:black_concrete_stairs":5,"vanilla_plus:black_concrete_powder_stairs":3,"minecraft:dirt":29,"minecraft:sand":2,"vanilla_plus:light_blue_terracotta_stairs":2,"vanilla_plus:sand_stairs":2,"vanilla_plus:sea_lantern_stairs":1,"vanilla_plus:oak_log":1,"vanilla_plus:glowstone_stairs":1,"minecraft:barrier":2,"vanilla_plus:grass_block_stairs":1,"vanilla_plus:dirt_stairs":6,"vanilla_plus:black_stained_glass_stairs":5,"minecraft:stone":5,"vanilla_plus:block_of_amethyst_stairs":5,"vanilla_plus:dirt_slab":17,"vanilla_plus:black_terracotta_stairs":3},"minecraft:custom":{"minecraft:time_since_rest":54594,"minecraft:crouch_one_cm":2020,"minecraft:sprint_one_cm":3851,"minecraft:play_time":54594,"minecraft:walk_one_cm":19461,"minecraft:sneak_time":550,"minecraft:drop":17,"minecraft:jump":37,"minecraft:leave_game":10,"minecraft:time_since_death":54594,"minecraft:total_world_time":54986,"minecraft:fly_one_cm":26591}},"DataVersion":2975}